gemini_tree_token_counter/__init__.py
gemini_tree_token_counter/main.py
gemini_tree_token_counter-0.1.6.dist-info/licenses/LICENSE
gemini_tree_token_counter-0.1.6.dist-info/METADATA
gemini_tree_token_counter-0.1.6.dist-info/WHEEL
gemini_tree_token_counter-0.1.6.dist-info/entry_points.txt
gemini_tree_token_counter-0.1.6.dist-info/top_level.txt
gemini_tree_token_counter-0.1.6.dist-info/RECORD
