Metadata-Version: 2.4
Name: gemini-tree-token-counter
Version: 0.1.6
Summary: Estimate tokens for Gemini and display tree from local/git sources.
Author-email: Sakasegawa <nyosegawa@gmail.com>
License: MIT License
Project-URL: Homepage, https://github.com/nyosegawa/gemini-tree-token-counter
Project-URL: Bug Tracker, https://github.com/nyosegawa/gemini-tree-token-counter/issues
Classifier: Programming Language :: Python :: 3
Classifier: License :: OSI Approved :: MIT License
Classifier: Operating System :: OS Independent
Requires-Python: >=3.7
License-File: LICENSE
Dynamic: license-file
